{
    "swagger": "2.0",
    "info": {
        "contact": {
            "name": "API Support",
            "url": "http://www.swagger.io/support",
            "email": "support@swagger.io"
        },
        "license": {
            "name": "Apache 2.0",
            "url": "http://www.apache.org/licenses/LICENSE-2.0.html"
        }
    },
    "paths": {
        "/user": {
            "post": {
                "description": "提交用户信息",
                "tags": [
                    "用户"
                ],
                "summary": "Add an user",
                "parameters": [
                    {
                        "type": "integer",
                        "description": "ID",
                        "name": "id",
                        "in": "formData",
                        "required": true
                    },
                    {
                        "type": "string",
                        "description": "姓名",
                        "name": "name",
                        "in": "formData",
                        "required": true
                    },
                    {
                        "type": "string",
                        "description": "类别",
                        "name": "userType",
                        "in": "formData",
                        "required": true
                    }
                ],
                "responses": {
                    "200": {
                        "description": "OK",
                        "schema": {
                            "$ref": "#/definitions/controllers.Res"
                        }
                    }
                }
            }
        },
        "/user/{id}": {
            "get": {
                "description": "获取用户信息",
                "tags": [
                    "用户"
                ],
                "summary": "Get an user",
                "parameters": [
                    {
                        "type": "integer",
                        "description": "ID",
                        "name": "id",
                        "in": "path",
                        "required": true
                    }
                ],
                "responses": {
                    "200": {
                        "description": "ok",
                        "schema": {
                            "type": "string"
                        }
                    }
                }
            }
        }
    },
    "definitions": {
        "controllers.Res": {
            "type": "object",
            "properties": {
                "id": {
                    "type": "string"
                },
                "name": {
                    "type": "string"
                },
                "userType": {
                    "type": "string"
                }
            }
        }
    }
}